LICENSE
MANIFEST.in
README.rst
setup.py
fraktur/__init__.py
fraktur/__main__.py
fraktur/code.py
fraktur/fraktur.py
fraktur.egg-info/PKG-INFO
fraktur.egg-info/SOURCES.txt
fraktur.egg-info/dependency_links.txt
fraktur.egg-info/top_level.txt