Metadata-Version: 1.1
Name: fraktur
Version: 1.0.2
Summary: 𝔠𝔬𝔫𝔳𝔢𝔯𝔱 𝔱𝔥𝔢 𝔩𝔞𝔱𝔦𝔫 𝔞𝔩𝔭𝔥𝔞𝔟𝔢𝔱 𝔱𝔬 𝔣𝔯𝔞𝔨𝔱𝔲𝔯 𝔲𝔫𝔦𝔠𝔬𝔡𝔢 𝔠𝔥𝔞𝔯𝔞𝔠𝔱𝔢𝔯𝔰
Home-page: http://github.com/carpedm20/fraktur
Author: Taehoon Kim
Author-email: carpedm20@gmail.com
License: BSD License
Keywords: fraktur
Platform: UNKNOWN
Classifier: Development Status :: 2 - Pre-Alpha
Classifier: Environment :: Console
Classifier: Intended Audience :: Developers
Classifier: License :: OSI Approved :: BSD License
Classifier: Operating System :: OS Independent
Classifier: Programming Language :: Python
Classifier: Programming Language :: Python :: 2
Classifier: Programming Language :: Python :: 2.6
Classifier: Programming Language :: Python :: 2.7
Classifier: Programming Language :: Python :: 3
Classifier: Programming Language :: Python :: 3.1
Classifier: Programming Language :: Python :: 3.2
Classifier: Programming Language :: Python :: 3.3
Classifier: Programming Language :: Python :: Implementation :: CPython
Classifier: Programming Language :: Python :: Implementation :: PyPy
Classifier: Topic :: Software Development :: Libraries :: Python Modules
